forbids/__init__.py
forbids/init.py
forbids/schema.py
forbids/validation.py
forbids/cli/__init__.py
forbids/cli/run.py
forbids/config/mri_tags.json
forbids-0.0.2rc149.post1.dist-info/entry_points.txt
forbids-0.0.2rc149.post1.dist-info/licenses/LICENSE
forbids-0.0.2rc149.post1.dist-info/WHEEL
forbids-0.0.2rc149.post1.dist-info/METADATA
forbids-0.0.2rc149.post1.dist-info/RECORD
