Metadata-Version: 2.4
Name: forbids
Version: 0.0.2rc149.post1
Summary: forBIDS - BIDS protocol compliance validation
Author-email: Basile Pinsard <basile.pinsard@gmail.com>
Requires-Python: >=3.11.0
Classifier: Development Status :: 3 - Alpha
Classifier: Intended Audience :: Developers
Classifier: License :: OSI Approved :: MIT License
Classifier: Programming Language :: Python :: 3 :: Only
Classifier: Programming Language :: Python :: 3.11
License-File: LICENSE
Requires-Dist: pybids
Requires-Dist: apischema
Requires-Dist: openapi-schema-validator
Requires-Dist: coloredlogs
Requires-Dist: pyspark>=3.0.0 ; extra == "spark"
Requires-Dist: bandit[toml]==1.7.10 ; extra == "test"
Requires-Dist: black==24.8.0 ; extra == "test"
Requires-Dist: check-manifest==0.49 ; extra == "test"
Requires-Dist: flake8-bugbear==24.8.19 ; extra == "test"
Requires-Dist: flake8-docstrings ; extra == "test"
Requires-Dist: flake8-formatter_junit_xml ; extra == "test"
Requires-Dist: flake8 ; extra == "test"
Requires-Dist: flake8-pyproject ; extra == "test"
Requires-Dist: pre-commit==3.8.0 ; extra == "test"
Requires-Dist: pylint==3.3.1 ; extra == "test"
Requires-Dist: pylint_junit ; extra == "test"
Requires-Dist: pytest-cov==5.0.0 ; extra == "test"
Requires-Dist: pytest-mock<3.14.1 ; extra == "test"
Requires-Dist: pytest-runner ; extra == "test"
Requires-Dist: pytest==8.3.3 ; extra == "test"
Requires-Dist: pytest-github-actions-annotate-failures ; extra == "test"
Requires-Dist: shellcheck-py==0.10.0.1 ; extra == "test"
Project-URL: Documentation, https://github.com/UNFMontreal/forbids
Project-URL: Source, https://github.com/UNFMontreal/forbids
Project-URL: Tracker, https://github.com/UNFMontreal/forbids/issues
Provides-Extra: spark
Provides-Extra: test
